sqlalchemy_pytds/__init__.py
sqlalchemy_pytds/connector.py
sqlalchemy_pytds/dialect.py
sqlalchemy_pytds/requirements.py
sqlalchemy_pytds-0.3.4.dist-info/LICENSE
sqlalchemy_pytds-0.3.4.dist-info/METADATA
sqlalchemy_pytds-0.3.4.dist-info/WHEEL
sqlalchemy_pytds-0.3.4.dist-info/entry_points.txt
sqlalchemy_pytds-0.3.4.dist-info/top_level.txt
sqlalchemy_pytds-0.3.4.dist-info/RECORD
